spectoconvo/__init__.py
spectoconvo/spectoconvo.py
spectoconvo/fonts/NotoSans-Regular.ttf
spectoconvo/fonts/NotoSansJP-SemiBold.ttf
spectoconvo/fonts/NotoSansKR-SemiBold.ttf
spectoconvo/fonts/NotoSansSC-Bold.ttf
spectoconvo-0.1.4.dist-info/LICENSE
spectoconvo-0.1.4.dist-info/METADATA
spectoconvo-0.1.4.dist-info/WHEEL
spectoconvo-0.1.4.dist-info/top_level.txt
spectoconvo-0.1.4.dist-info/RECORD
