Metadata-Version: 2.1
Name: spectoconvo
Version: 0.1.4
Summary: A package to embed messages into spectrograms
Author: Mitchell Gerrard
License: MIT
Project-URL: Homepage, https://github.com/Mitchell-Gerrard/spectoconvo
Classifier: Programming Language :: Python :: 3
Classifier: License :: OSI Approved :: MIT License
Classifier: Operating System :: OS Independent
Requires-Python: >=3.6
License-File: LICENSE
Requires-Dist: numpy
Requires-Dist: scipy
Requires-Dist: matplotlib
Requires-Dist: Pillow
Requires-Dist: scikit-image
Requires-Dist: setuptools
Requires-Dist: pydub
